buildbot_pipelines/__init__.py
buildbot_pipelines/configurator.py
buildbot_pipelines/package_loader.py
buildbot_pipelines/yaml_loader.py
buildbot_pipelines/schedulers/__init__.py
buildbot_pipelines/schedulers/anycodebasescheduler.py
buildbot_pipelines/steps/__init__.py
buildbot_pipelines/steps/gitforchange.py
buildbot_pipelines/steps/runner.py
buildbot_pipelines/steps/spawner.py
buildbot_pipelines/tests/__init__.py
buildbot_pipelines/tests/test_integration.py
buildbot_pipelines/tests/test_yaml_loader.py
buildbot_pipelines-0.1.0.dist-info/DESCRIPTION.rst
buildbot_pipelines-0.1.0.dist-info/METADATA
buildbot_pipelines-0.1.0.dist-info/RECORD
buildbot_pipelines-0.1.0.dist-info/WHEEL
buildbot_pipelines-0.1.0.dist-info/metadata.json
buildbot_pipelines-0.1.0.dist-info/top_level.txt
